fanfou_cli-0.1.20.dist-info/DESCRIPTION.rst
fanfou_cli-0.1.20.dist-info/METADATA
fanfou_cli-0.1.20.dist-info/RECORD
fanfou_cli-0.1.20.dist-info/WHEEL
fanfou_cli-0.1.20.dist-info/entry_points.txt
fanfou_cli-0.1.20.dist-info/metadata.json
fanfou_cli-0.1.20.dist-info/top_level.txt
fanfoucli/__init__.py
fanfoucli/cli.py
fanfoucli/config.py
fanfoucli/fan.py
fanfoucli/util.py
