Metadata-Version: 2.0
Name: fanfou-cli
Version: 0.1.20
Summary: Fanfou Command Line Client
Home-page: https://github.com/j178/fanfou-cli
Author: John Jiang
Author-email: nigelchiang@outlook.com
License: MIT
Keywords: internet,oauth,sns
Platform: UNKNOWN
Requires-Dist: arrow
Requires-Dist: requests-oauthlib
